lfprop/__init__.py
lfprop/data/__init__.py
lfprop/data/custom_datasets.py
lfprop/data/dataloaders.py
lfprop/data/datasets.py
lfprop/data/transforms.py
lfprop/evaluation/__init__.py
lfprop/evaluation/evaluate.py
lfprop/model/__init__.py
lfprop/model/activations.py
lfprop/model/custom_resnet.py
lfprop/model/model_definitions.py
lfprop/model/models.py
lfprop/model/spiking_networks.py
lfprop/propagation/__init__.py
lfprop/propagation/propagator_lxt.py
lfprop/propagation/propagator_regression.py
lfprop/propagation/propagator_snn.py
lfprop/propagation/propagator_vit.py
lfprop/rewards/__init__.py
lfprop/rewards/reward_functions.py
lfprop/rewards/rewards.py
lfprop/utils/__init__.py
lfprop/utils/utils.py
lfprop-1.0.0.dist-info/LICENSE
lfprop-1.0.0.dist-info/METADATA
lfprop-1.0.0.dist-info/WHEEL
lfprop-1.0.0.dist-info/RECORD
